somanet_test_suite/__init__.py
somanet_test_suite/communication/BaseCANOpen.py
somanet_test_suite/communication/BaseEtherCAT.py
somanet_test_suite/communication/BaseFileSystem.py
somanet_test_suite/communication/__init__.py
somanet_test_suite/communication/esi.py
somanet_test_suite/communication/can/CANMaster.py
somanet_test_suite/communication/can/__init__.py
somanet_test_suite/communication/ethercat/IgHMaster.py
somanet_test_suite/communication/ethercat/SOEMMaster.py
somanet_test_suite/communication/ethercat/__init__.py
somanet_test_suite/communication/uart/__init__.py
somanet_test_suite/communication/uart/somanet_bootloader_uart.py
somanet_test_suite/communication/uart/uart.py
somanet_test_suite/daq/__init__.py
somanet_test_suite/daq/daq_labjack.py
somanet_test_suite/hardware_description_builder/__init__.py
somanet_test_suite/hardware_description_builder/build_hardware_description_json.py
somanet_test_suite/hardware_description_builder/dataformat.py
somanet_test_suite/psu/__init__.py
somanet_test_suite/psu/psu_ea.py
somanet_test_suite/sanssouci/__init__.py
somanet_test_suite/sanssouci/sanssouci.py
somanet_test_suite-1.1.5.data/scripts/psu_controller
somanet_test_suite-1.1.5.data/scripts/somanet_hw_description_builder
somanet_test_suite-1.1.5.dist-info/LICENSE
somanet_test_suite-1.1.5.dist-info/METADATA
somanet_test_suite-1.1.5.dist-info/WHEEL
somanet_test_suite-1.1.5.dist-info/top_level.txt
somanet_test_suite-1.1.5.dist-info/RECORD
