Metadata-Version: 2.1
Name: somanet_test_suite
Version: 1.1.5
Summary: A collection of different scripts and drivers (PSU, EtherCAT, Labjack,...)
Author: Synapticon GmbH
Author-email: hstroetgen@synapticon.com
License: MIT
Keywords: power supply unit,psu,daq,Labjack,Elektro-Automation,EtherCAT,IgH,Synapticon,CANopen,CANSOEM
Classifier: Programming Language :: Python :: 3.6
Classifier: Operating System :: POSIX :: Linux
Classifier: Topic :: System :: Hardware :: Hardware Drivers
Requires-Python: >=3.6
License-File: LICENSE
Requires-Dist: pyserial >=3.4
Requires-Dist: crcmod
Requires-Dist: numpy
Requires-Dist: labjack-ljm
Requires-Dist: xmltodict
Requires-Dist: pysoem ==1.1.6
Requires-Dist: elevate
Requires-Dist: canopen >=2.0
Requires-Dist: bitstruct
